holocontour/__init__.py
holocontour/configs/__init__.py
holocontour/configs/sample_config.yaml
holocontour/contour/__init__.py
holocontour/contour/contour_detection.py
holocontour/contour/morpho_custom.py
holocontour/contour/toolsbox.py
"holocontour/data/001-1524.pgm(1,312)-Z35.00.png"
"holocontour/data/001-1804.pgm(887,842)-Z32.50.png"
"holocontour/data/001-1915.pgm(673,287)-Z48.25.png"
"holocontour/data/001-1933.pgm(792,187)-Z29.75.png"
"holocontour/data/001-2086.pgm(745,745)-Z41.00.png"
"holocontour/data/001-2263.pgm(910,810)-Z31.75.png"
"holocontour/data/001-2300.pgm(710,697)-Z31.75.png"
"holocontour/data/001-4923.pgm(406,428)-Z43.50.png"
holocontour/data/__init__.py
holocontour/image/__init__.py
holocontour/image/processing.py
holocontour/image/region_growing.py
holocontour/image/safe_image_properties.py
holocontour/image/structure_forest.py
holocontour/image/visual.py
holocontour/model/__init__.py
holocontour/model/model.yml
holocontour/pipeline/__init__.py
holocontour/pipeline/pipeline_runner.py
holocontour-0.1.6.dist-info/licenses/LICENSE
holocontour-0.1.6.dist-info/METADATA
holocontour-0.1.6.dist-info/WHEEL
holocontour-0.1.6.dist-info/top_level.txt
holocontour-0.1.6.dist-info/RECORD
