Metadata-Version: 2.4
Name: holocontour
Version: 0.1.6
Summary: A minimalist toolkit for holographic plankton image segmentation
Author-email: Mojtaba Masoudi <mojmas@noc.ac.uk>
Requires-Python: >=3.8
License-File: LICENSE
Requires-Dist: numpy
Requires-Dist: opencv-contrib-python
Requires-Dist: matplotlib
Requires-Dist: scikit-image
Requires-Dist: pyyaml
Requires-Dist: tqdm
Dynamic: license-file
